racks_on_tabs/__init__.py
racks_on_tabs/__main__.py
racks_on_tabs/app.py
racks_on_tabs/static/app.css
racks_on_tabs/static/app.js
racks_on_tabs/static/favicon.png
racks_on_tabs/templates/index.html
racks_on_tabs/templates/table_rows.html
racks_on_tabs-0.1.2.dist-info/entry_points.txt
racks_on_tabs-0.1.2.dist-info/LICENSE
racks_on_tabs-0.1.2.dist-info/WHEEL
racks_on_tabs-0.1.2.dist-info/METADATA
racks_on_tabs-0.1.2.dist-info/RECORD
