Metadata-Version: 2.1
Name: racks-on-tabs
Version: 0.1.2
Summary: Command line app for browsing CSV files with row lazy loading.
Home-page: https://github.com/alexjuda/racks-on-tabs
License: MIT
Author: Alexander Juda
Author-email: alexanderjuda@gmail.com
Requires-Python: >=3.8,<4.0
Classifier: License :: OSI Approved :: MIT License
Classifier: Programming Language :: Python :: 3
Classifier: Programming Language :: Python :: 3.8
Requires-Dist: flask (>=1.1.2,<2.0.0)
Requires-Dist: waitress (>=1.4.4,<2.0.0)
Project-URL: Repository, https://github.com/alexjuda/racks-on-tabs
